dbchat/__init__.py
dbchat-0.1.0.dist-info/METADATA
dbchat-0.1.0.dist-info/WHEEL
dbchat-0.1.0.dist-info/LICENSE
dbchat-0.1.0.dist-info/RECORD
